{"name":"North America","slug":"na","locales":["en_US"],"hostname":"prod.na1.lol.riotgames.com","region_tag":"na1","services":[{"name":"Boards","slug":"boards","status":"online","incidents":[]},{"name":"Game","slug":"game","status":"online","incidents":[{"id":2395,"active":true,"created_at":"2015-05-14T22:10:25.000Z","updates":[{"id":2730,"author":"","content":"We've temporarily disabled Rumble and Viktor due to an in-game bug and are working on fixing the problem.","severity":"info","created_at":"2015-05-14T22:18:35.000Z","updated_at":"2015-05-14T22:19:21.000Z","translations":[]}]}]},{"name":"Store","slug":"store","status":"online","incidents":[{"id":2377,"active":true,"created_at":"2015-05-08T23:51:02.000Z","updates":[{"id":2728,"author":"","content":"We're aware that some players are still experiencing a black screen when loading the store and are working to resolve this issue.","severity":"info","created_at":"2015-05-14T18:13:01.000Z","updated_at":"2015-05-14T18:13:01.000Z","translations":[]},{"id":2696,"author":"","content":"We're currently investigating an issue where some players are seeing a black screen in the store. ","severity":"info","created_at":"2015-05-08T23:51:19.000Z","updated_at":"2015-05-08T23:51:19.000Z","translations":[]}]}]},{"name":"Website","slug":"web","status":"online","incidents":[]}]}